<expo>
  <eventRegistry>
    <events>
      <applicationList>
        <assignedStand>
          <area>0.0</area>
          <description/>
        </assignedStand>
        <author>
          <email/>
          <isAdmin>false</isAdmin>
          <name/>
          <username/>
        </author>
        <companyTradeName>fdafdsf</companyTradeName>
        <description/>
        <displayProducts>
          <name>fasfdsf</name>
        </displayProducts>
        <displayProducts>
          <name>fasdfasdf</name>
        </displayProducts>
        <intendedStandArea>43.0</intendedStandArea>
        <numberOfInvitations>43</numberOfInvitations>
        <phoneNumber>423423</phoneNumber>
        <staffReviewers>
          <email>1140825@isep.ipp.pt</email>
          <isAdmin>false</isAdmin>
          <name>Vitor Silva</name>
          <password>0.0737021364</password>
          <username>vitorsilva</username>
        </staffReviewers>
        <status>accepted</status>
        <vatNumber>3223423</vatNumber>
      </applicationList>
      <applicationList>
        <assignedStand>
          <area>0.0</area>
          <description/>
        </assignedStand>
        <author>
          <email>1050469@isep.ipp.pt</email>
          <isAdmin>false</isAdmin>
          <name>Filipe Couto</name>
          <password>0.0737021364</password>
          <username>filipecouto</username>
        </author>
        <companyTradeName>testeapp1</companyTradeName>
        <description/>
        <displayProducts>
          <name>132</name>
        </displayProducts>
        <displayProducts>
          <name>56</name>
        </displayProducts>
        <intendedStandArea>12.0</intendedStandArea>
        <keywords>
          <value>21321</value>
        </keywords>
        <keywords>
          <value>apple</value>
        </keywords>
        <keywords>
          <value>orange</value>
        </keywords>
        <numberOfInvitations>21</numberOfInvitations>
        <phoneNumber>654461</phoneNumber>
        <staffReviewers>
          <email>1140825@isep.ipp.pt</email>
          <isAdmin>false</isAdmin>
          <name>Vitor Silva</name>
          <password>0.0737021364</password>
          <username>vitorsilva</username>
        </staffReviewers>
        <status>accepted</status>
        <vatNumber>6544</vatNumber>
        <workshopList>
          <duration>5</duration>
          <interestedUsers>991781692</interestedUsers>
          <interestedUsers>1842708950</interestedUsers>
          <necessaryEquipment>lol</necessaryEquipment>
          <necessaryEquipment>lel</necessaryEquipment>
          <room>5</room>
          <workshopDescription>wk1</workshopDescription>
          <workshopTitle>wk1</workshopTitle>
        </workshopList>
      </applicationList>
      <applicationList>
        <assignedStand>
          <area>0.0</area>
          <description/>
        </assignedStand>
        <author>
          <email>1050469@isep.ipp.pt</email>
          <isAdmin>false</isAdmin>
          <name>Filipe Couto</name>
          <password>0.0737021364</password>
          <username>filipecouto</username>
        </author>
        <companyTradeName>testeapp2</companyTradeName>
        <description/>
        <displayProducts>
          <name>pn</name>
        </displayProducts>
        <displayProducts>
          <name>onlç</name>
        </displayProducts>
        <intendedStandArea>21.0</intendedStandArea>
        <keywords>
          <value>banana</value>
        </keywords>
        <keywords>
          <value>apple</value>
        </keywords>
        <numberOfInvitations>21</numberOfInvitations>
        <phoneNumber>79846513</phoneNumber>
        <staffReviewers>
          <email>1140825@isep.ipp.pt</email>
          <isAdmin>false</isAdmin>
          <name>Vitor Silva</name>
          <password>0.0737021364</password>
          <username>vitorsilva</username>
        </staffReviewers>
        <status>accepted</status>
        <vatNumber>9874651</vatNumber>
        <workshopList>
          <duration>5</duration>
          <interestedUsers>991781692</interestedUsers>
          <interestedUsers>1842708950</interestedUsers>
          <necessaryEquipment>lol</necessaryEquipment>
          <necessaryEquipment>lel</necessaryEquipment>
          <room>5</room>
          <workshopDescription>owi</workshopDescription>
          <workshopTitle>gfhob</workshopTitle>
        </workshopList>
        <workshopList>
          <duration>5</duration>
          <interestedUsers>991781692</interestedUsers>
          <room>5</room>
          <workshopDescription>iugb</workshopDescription>
          <workshopTitle>wk2</workshopTitle>
        </workshopList>
      </applicationList>
      <attendees>
        <email>1050469@isep.ipp.pt</email>
        <isAdmin>false</isAdmin>
        <name>Filipe Couto</name>
        <password>0.0737021364</password>
        <username>filipecouto</username>
      </attendees>
      <attendees>
        <email>1140951@isep.ipp.pt</email>
        <isAdmin>false</isAdmin>
        <name>Vitor Paiva</name>
        <password>0.0737021364</password>
        <username>vitorpaiva</username>
      </attendees>
      <date>
        <day>2</day>
        <month>2</month>
        <year>2002</year>
      </date>
      <deadline>
        <day>1</day>
        <month>1</month>
        <year>2002</year>
      </deadline>
      <description>dasdasd</description>
      <id>0</id>
      <isOpenToApplications>true</isOpenToApplications>
      <location>asd</location>
      <organisers>
        <email>1171316@isep.ipp.pt</email>
        <isAdmin>false</isAdmin>
        <name>Diogo Capela</name>
        <password>0.0737021364</password>
        <username>diogocapela</username>
      </organisers>
      <staffMembers>
        <email>1140825@isep.ipp.pt</email>
        <isAdmin>false</isAdmin>
        <name>Vitor Silva</name>
        <password>0.0737021364</password>
        <username>vitorsilva</username>
      </staffMembers>
      <title>dasdas</title>
      <type>exhibition</type>
    </events>
    <events>
      <date>
        <day>21</day>
        <month>7</month>
        <year>2018</year>
      </date>
      <deadline>
        <day>1</day>
        <month>7</month>
        <year>2018</year>
      </deadline>
      <description>ouiv</description>
      <id>0</id>
      <isOpenToApplications>true</isOpenToApplications>
      <location>ihv</location>
      <organisers>
        <email>1171316@isep.ipp.pt</email>
        <isAdmin>false</isAdmin>
        <name>Diogo Capela</name>
        <password>0.0737021364</password>
        <username>diogocapela</username>
      </organisers>
      <staffMembers>
        <email>1090441@isep.ipp.pt</email>
        <isAdmin>false</isAdmin>
        <name>Rafael Marques</name>
        <password>0.0737021364</password>
        <username>rafaelmarques</username>
      </staffMembers>
      <title>ljobl</title>
      <type>exhibition</type>
    </events>
  </eventRegistry>
  <loggedInUser>
    <email>1140951@isep.ipp.pt</email>
    <isAdmin>false</isAdmin>
    <name>Vitor Paiva</name>
    <password>0.0737021364</password>
    <username>vitorpaiva</username>
  </loggedInUser>
  <userRegistry>
    <users>
      <email>admin@isep.ipp.pt</email>
      <isAdmin>true</isAdmin>
      <name>Administrator</name>
      <password>0.0737021364</password>
      <username>admin</username>
    </users>
    <users>
      <email>1171316@isep.ipp.pt</email>
      <isAdmin>false</isAdmin>
      <name>Diogo Capela</name>
      <password>0.0737021364</password>
      <username>diogocapela</username>
    </users>
    <users>
      <email>1140825@isep.ipp.pt</email>
      <isAdmin>false</isAdmin>
      <name>Vitor Silva</name>
      <password>0.0737021364</password>
      <username>vitorsilva</username>
    </users>
    <users>
      <email>1090441@isep.ipp.pt</email>
      <isAdmin>false</isAdmin>
      <name>Rafael Marques</name>
      <password>0.0737021364</password>
      <username>rafaelmarques</username>
    </users>
    <users>
      <email>1050469@isep.ipp.pt</email>
      <isAdmin>false</isAdmin>
      <name>Filipe Couto</name>
      <password>0.0737021364</password>
      <username>filipecouto</username>
    </users>
    <users>
      <email>1140951@isep.ipp.pt</email>
      <isAdmin>false</isAdmin>
      <name>Vitor Paiva</name>
      <password>0.0737021364</password>
      <username>vitorpaiva</username>
    </users>
  </userRegistry>
</expo>
